vistickedword.py
vistickedword-0.9.5.dist-info/LICENSE
vistickedword-0.9.5.dist-info/WHEEL
vistickedword-0.9.5.dist-info/METADATA
vistickedword-0.9.5.dist-info/RECORD
