Metadata-Version: 2.1
Name: vistickedword
Version: 0.9.5
Summary: Library to split sticked Vietnamese words
Home-page: https://github.com/hongquan/ViStickedWord
License: MIT
Author: Nguyễn Hồng Quân
Author-email: ng.hong.quan@gmail.com
Requires-Python: >=3.6,<4.0
Classifier: Development Status :: 4 - Beta
Classifier: Intended Audience :: Developers
Classifier: License :: OSI Approved :: MIT License
Classifier: Natural Language :: Vietnamese
Classifier: Programming Language :: Python :: 3
Classifier: Programming Language :: Python :: 3 :: Only
Classifier: Programming Language :: Python :: 3.6
Classifier: Programming Language :: Python :: 3.7
Classifier: Programming Language :: Python :: 3.8
Classifier: Topic :: Software Development :: Libraries :: Python Modules
Classifier: Topic :: Text Processing :: Linguistic
Requires-Dist: single-version (>=1.1,<2.0)
Project-URL: Repository, https://github.com/hongquan/ViStickedWord.git
